bs_loco/__init__.py
bs_loco/__main__.py
bs_loco/batch_archive_msgs.py
bs_loco/batch_updown_templ.py
bs_loco/config.py
bs_loco/constants.py
bs_loco/loco_server.py
bs_loco/loco_template.py
bs_loco/util.py
bs_loco/xloco.py
bs_loco/corrprov/__init__.py
bs_loco/corrprov/awssns_sms.py
bs_loco/corrprov/bulksms_sms.py
bs_loco/corrprov/logfile_email.py
bs_loco/corrprov/logfile_sms.py
bs_loco/corrprov/provider.py
bs_loco/corrprov/provider_email.py
bs_loco/corrprov/provider_sms.py
bs_loco/corrprov/smtp_email.py
bs_loco/db/__init__.py
bs_loco/db/dao/postgresql/__init__.py
bs_loco/db/dao/postgresql/config.py
bs_loco/db/dao/postgresql/config_insert.py
bs_loco/db/dao/postgresql/config_lock_one.py
bs_loco/db/dao/postgresql/config_search.py
bs_loco/db/dao/postgresql/config_select_one.py
bs_loco/db/dao/postgresql/config_update.py
bs_loco/db/dao/postgresql/corr_prov.py
bs_loco/db/dao/postgresql/corr_prov_cfg.py
bs_loco/db/dao/postgresql/corr_prov_cfg_delete_one.py
bs_loco/db/dao/postgresql/corr_prov_cfg_insert.py
bs_loco/db/dao/postgresql/corr_prov_cfg_lock_one.py
bs_loco/db/dao/postgresql/corr_prov_cfg_select_one.py
bs_loco/db/dao/postgresql/corr_prov_cfg_update.py
bs_loco/db/dao/postgresql/corr_prov_delete_one.py
bs_loco/db/dao/postgresql/corr_prov_for_service.py
bs_loco/db/dao/postgresql/corr_prov_insert.py
bs_loco/db/dao/postgresql/corr_prov_lock_one.py
bs_loco/db/dao/postgresql/corr_prov_select_one.py
bs_loco/db/dao/postgresql/corr_prov_update.py
bs_loco/db/dao/postgresql/corr_type.py
bs_loco/db/dao/postgresql/corr_type_allow.py
bs_loco/db/dao/postgresql/corr_type_allow_delete_one.py
bs_loco/db/dao/postgresql/corr_type_allow_insert.py
bs_loco/db/dao/postgresql/corr_type_allow_lock_one.py
bs_loco/db/dao/postgresql/corr_type_allow_regex_for_type.py
bs_loco/db/dao/postgresql/corr_type_allow_select_one.py
bs_loco/db/dao/postgresql/corr_type_allow_update.py
bs_loco/db/dao/postgresql/corr_type_insert.py
bs_loco/db/dao/postgresql/corr_type_lock_one.py
bitsmiths_loco-2.2.1.dist-info/LICENCE
bitsmiths_loco-2.2.1.dist-info/METADATA
bitsmiths_loco-2.2.1.dist-info/WHEEL
bitsmiths_loco-2.2.1.dist-info/entry_points.txt
bitsmiths_loco-2.2.1.dist-info/top_level.txt
bitsmiths_loco-2.2.1.dist-info/RECORD
